mr_menu/__init__.py
mr_menu/exceptions.py
mr_menu/generator.py
mr_menu/simple.py
mr_menu-0.1.dist-info/LICENSE
mr_menu-0.1.dist-info/METADATA
mr_menu-0.1.dist-info/WHEEL
mr_menu-0.1.dist-info/top_level.txt
mr_menu-0.1.dist-info/RECORD
