Metadata-Version: 2.1
Name: mr-menu
Version: 0.1
Summary: Complex and simple nested menus
Author-email: Soumyo Deep Gupta <deep.main.ac@gmail.com>
Maintainer-email: Soumyo Deep Gupta <deep.main.ac@gmail.com>
License: MIT License
Project-URL: GitHub, https://github.com/d33p0st/mr-menu
Project-URL: Issues, https://github.com/d33p0st/mr-menu/issues
Project-URL: Pull Requests, https://github.com/d33p0st/mr-menu/pulls
Keywords: d33p0st,mr-menu,menu,nested-menu,complex-menu
Classifier: Development Status :: 4 - Beta
Classifier: Topic :: Software Development :: Libraries :: Python Modules
Classifier: Programming Language :: Python :: 3.10
Classifier: Programming Language :: Python :: 3.11
Classifier: Programming Language :: Python :: 3.12
Classifier: License :: OSI Approved :: MIT License
Classifier: Operating System :: OS Independent
Requires-Python: >=3.10
License-File: LICENSE
Requires-Dist: pytest
Requires-Dist: pytest-cov
